[
  {
    "mu_err": 6.638375968031261,
    "max_err": 54.43009765625,
    "rRMSE": 8.90097411530114,
    "F10": 19.130434782608695,
    "R2": 0.9879971887270731,
    "tag": "Biasi_bare",
    "hybrid": false,
    "limited": false,
    "n_train": 0,
    "model": "correlation"
  },
  {
    "mu_err": 4.556917871120298,
    "max_err": 40.03075,
    "rRMSE": 6.346728955473085,
    "F10": 8.695652173913043,
    "R2": 0.9953330112924345,
    "tag": "DNN_pure_80",
    "hybrid": false,
    "limited": false,
    "n_train": 7350,
    "n_models": 10,
    "train_time_s": 267.1654417514801
  },
  {
    "mu_err": 4.233959180620187,
    "max_err": 36.975289062499996,
    "rRMSE": 5.933415412944376,
    "F10": 6.630434782608696,
    "R2": 0.9960697450886493,
    "tag": "DNN_Biasi_hybrid_80",
    "hybrid": true,
    "limited": false,
    "n_train": 7350,
    "n_models": 10,
    "train_time_s": 156.13958096504211
  },
  {
    "mu_err": 91.75036467413757,
    "max_err": 1010.0553903259138,
    "rRMSE": 159.76103324895539,
    "F10": 86.95652173913044,
    "R2": 0.4005961955059646,
    "tag": "DNN_pure_9",
    "hybrid": false,
    "limited": true,
    "n_train": 9,
    "n_models": 10,
    "train_time_s": 0.8413519859313965
  },
  {
    "mu_err": 7.411366277047344,
    "max_err": 67.86752734375,
    "rRMSE": 10.359337059841327,
    "F10": 23.043478260869566,
    "R2": 0.9877102046487642,
    "tag": "DNN_Biasi_hybrid_9",
    "hybrid": true,
    "limited": true,
    "n_train": 9,
    "n_models": 10,
    "train_time_s": 0.6890649795532227
  }
]